hmd/__init__.py
hmd/main.py
hmd/controllers/__init__.py
hmd/controllers/base.py
hmd/controllers/docker.py
hmd/core/__init__.py
hmd/core/exc.py
hmd/ext/__init__.py
hmd/plugins/__init__.py
hmd/templates/__init__.py
hmd_cli_app-1.2.616.dist-info/METADATA
hmd_cli_app-1.2.616.dist-info/WHEEL
hmd_cli_app-1.2.616.dist-info/entry_points.txt
hmd_cli_app-1.2.616.dist-info/top_level.txt
hmd_cli_app-1.2.616.dist-info/RECORD
