Metadata-Version: 2.1
Name: hmd-cli-app
Version: 1.2.616
Summary: Support tools for the HMD NeuronSphere development platform.
Author: Jim Majure
Author-email: jim.majure@hmdlabs.io
License: Apache 2.0
Requires-Dist: aws-secretsmanager-caching==1.1.3
Requires-Dist: boto3==1.36.22
Requires-Dist: botocore==1.36.23
Requires-Dist: cachetools==5.2.0
Requires-Dist: cement==3.0.6
Requires-Dist: certifi==2025.4.26
Requires-Dist: charset-normalizer==2.0.12
Requires-Dist: colorlog==6.6.0
Requires-Dist: durationpy==0.10
Requires-Dist: google-auth==2.9.1
Requires-Dist: hmd-cli-tools~=1.2.242
Requires-Dist: idna==3.10
Requires-Dist: inquirerpy==0.3.4
Requires-Dist: jinja2==3.1.6
Requires-Dist: jmespath==0.10.0
Requires-Dist: kubernetes==34.1.0
Requires-Dist: markupsafe==3.0.2
Requires-Dist: oauthlib==3.3.1
Requires-Dist: pfzy==0.3.4
Requires-Dist: prompt-toolkit==3.0.38
Requires-Dist: pyasn1==0.6.1
Requires-Dist: pyasn1-modules==0.4.2
Requires-Dist: python-dateutil==2.8.2
Requires-Dist: python-dotenv==1.1.1
Requires-Dist: pyyaml==6.0.1
Requires-Dist: requests==2.32.3
Requires-Dist: requests-oauthlib==1.3.1
Requires-Dist: rsa==4.8
Requires-Dist: s3transfer==0.11.2
Requires-Dist: six==1.16.0
Requires-Dist: urllib3==1.26.8
Requires-Dist: wcwidth==0.2.6
Requires-Dist: websocket-client==1.3.3
